xpybutil/__init__.py
xpybutil/compat.py
xpybutil/cursor.py
xpybutil/event.py
xpybutil/ewmh.py
xpybutil/font.py
xpybutil/icccm.py
xpybutil/image.py
xpybutil/keybind.py
xpybutil/keysymdef.py
xpybutil/motif.py
xpybutil/mousebind.py
xpybutil/rect.py
xpybutil/render.py
xpybutil/util.py
xpybutil/window.py
xpybutil/xinerama.py
xpybutil-0.0.6.data/data/share/doc/xpybutil/COPYING
xpybutil-0.0.6.data/data/share/doc/xpybutil/README.md
xpybutil-0.0.6.dist-info/COPYING
xpybutil-0.0.6.dist-info/METADATA
xpybutil-0.0.6.dist-info/WHEEL
xpybutil-0.0.6.dist-info/top_level.txt
xpybutil-0.0.6.dist-info/RECORD
