Metadata-Version: 2.1
Name: xpybutil
Version: 0.0.6
Summary: An incomplete xcb-util port plus some extras
Home-page: http://github.com/BurntSushi/xpybutil
Author-email: fmacrae.dev@gmail.com
Maintainer: Fenner Macrae
License: WTFPL
Platform: POSIX
